ovos_phal_plugin_ww_led/__init__.py
ovos_phal_plugin_ww_led/version.py
ovos_phal_plugin_ww_led-1.0.0.dist-info/LICENSE
ovos_phal_plugin_ww_led-1.0.0.dist-info/METADATA
ovos_phal_plugin_ww_led-1.0.0.dist-info/WHEEL
ovos_phal_plugin_ww_led-1.0.0.dist-info/entry_points.txt
ovos_phal_plugin_ww_led-1.0.0.dist-info/top_level.txt
ovos_phal_plugin_ww_led-1.0.0.dist-info/zip-safe
ovos_phal_plugin_ww_led-1.0.0.dist-info/RECORD
