Metadata-Version: 2.1
Name: ovos-phal-plugin-ww-led
Version: 1.0.0
Summary: A plugin to turn a LED on when a wakeword is detected
Home-page: https://github.com/smartgic/ovos-phal-plugin-ww-led
Author: Gaëtan Trellu (goldyfruit)
Author-email: gaetan.trellu@gmail.com
License: Apache-2.0
Classifier: Development Status :: 3 - Alpha
Classifier: Intended Audience :: Developers
Classifier: Topic :: Text Processing :: Linguistic
Classifier: License :: OSI Approved :: Apache Software License
Classifier: Programming Language :: Python :: 3.9
Classifier: Programming Language :: Python :: 3.10
Classifier: Programming Language :: Python :: 3.11
Classifier: Programming Language :: Python :: 3.12
License-File: LICENSE
Requires-Dist: json-database
Requires-Dist: ovos-bus-client
Requires-Dist: ovos-plugin-manager
Requires-Dist: RPi.GPIO
